visby/__init__.py
visby/activity_model.py
visby/crud.py
visby/database.py
visby/main.py
visby/measurement_model.py
visby/user_model.py
visby/version.py
visby-0.2.1.dist-info/LICENSE
visby-0.2.1.dist-info/METADATA
visby-0.2.1.dist-info/WHEEL
visby-0.2.1.dist-info/top_level.txt
visby-0.2.1.dist-info/RECORD
