Metadata-Version: 2.1
Name: visby
Version: 0.2.1
Author-email: Jakub Klawikowski <klawik.j@gmail.com>
Requires-Python: >=3.10
License-File: LICENSE
Requires-Dist: fastapi ==0.110.0
Requires-Dist: uvicorn ==0.29.0
Requires-Dist: httpx ==0.27.0
Requires-Dist: SQLAlchemy ==2.0.29
Requires-Dist: sqlmodel ==0.0.16
Requires-Dist: psycopg2-binary ==2.9.9
